gurk/__init__.py
gurk/main.py
gurk/cli/core.py
gurk/cli/info.py
gurk/cli/setup.py
gurk/cli/utils.py
gurk/config/README.md
gurk/config/default.yaml
gurk/config/enabled.yaml
gurk/config/configure/configure_bashrc.bash
gurk/config/configure/configure_filestructure.yaml
gurk/config/configure/configure_pinned_apps.txt
gurk/config/configure/configure_vscode_keybindings.jsonc
gurk/config/install/install_apt_packages.txt
gurk/config/install/install_conda_environments.jsonc
gurk/config/install/install_docker_images.jsonc
gurk/config/install/install_flatpak_packages.txt
gurk/config/install/install_js_repositories.txt
gurk/config/install/install_npm_packages.txt
gurk/config/install/install_pip_environments.jsonc
gurk/config/install/install_pipx_packages.txt
gurk/config/install/install_snap_packages.txt
gurk/config/install/install_vscode_extensions.txt
gurk/core/logger.py
gurk/core/scheduler.py
gurk/core/task_processor.py
gurk/scripts/bash/configure/checks.bash
gurk/scripts/bash/configure/simple_configurations.bash
gurk/scripts/bash/helpers/_interface.bash
gurk/scripts/bash/helpers/helpers.bash
gurk/scripts/bash/helpers/marking.bash
gurk/scripts/bash/helpers/processing.bash
gurk/scripts/bash/install/checks.bash
gurk/scripts/bash/install/conda.bash
gurk/scripts/bash/install/docker.bash
gurk/scripts/bash/install/isaac.bash
gurk/scripts/bash/install/nvidia.bash
gurk/scripts/bash/install/ros.bash
gurk/scripts/bash/install/simple_installations.bash
gurk/scripts/bash/uninstall/checks.bash
gurk/scripts/bash/uninstall/simple_uninstallations.bash
gurk/scripts/python/configure/checks.py
gurk/scripts/python/configure/simple_configurations.py
gurk/scripts/python/helpers/_interface.py
gurk/scripts/python/helpers/common.py
gurk/scripts/python/helpers/processing.py
gurk/scripts/python/install/checks.py
gurk/scripts/python/install/environments.py
gurk/scripts/python/install/js.py
gurk/scripts/python/install/package_managers.py
gurk/scripts/python/uninstall/checks.py
gurk/utils/cli.py
gurk-1.1.0.dist-info/licenses/LICENSE
gurk-1.1.0.dist-info/METADATA
gurk-1.1.0.dist-info/WHEEL
gurk-1.1.0.dist-info/entry_points.txt
gurk-1.1.0.dist-info/top_level.txt
gurk-1.1.0.dist-info/RECORD
