Metadata-Version: 2.4
Name: gurk
Version: 1.1.0
Summary: Contains anything related to setting up a new computer (desktop) system
Author-email: "Arturo J. Roberti" <arturo.roberti@outlook.com>
License: MIT License
Project-URL: Homepage, https://github.com/ArturoRoberti/gurk
Project-URL: Repository, https://github.com/ArturoRoberti/gurk
Project-URL: Issues, https://github.com/ArturoRoberti/gurk/issues
Project-URL: Documentation, https://github.com/ArturoRoberti/gurk#readme
Classifier: Programming Language :: Python :: 3
Classifier: License :: OSI Approved :: MIT License
Classifier: Operating System :: POSIX :: Linux
Classifier: Environment :: Console
Classifier: Topic :: System :: Installation/Setup
Classifier: Intended Audience :: End Users/Desktop
Requires-Python: >=3.10
License-File: LICENSE
Requires-Dist: click
Requires-Dist: rich
Requires-Dist: distro
Requires-Dist: ruamel.yaml
Requires-Dist: commentjson
Requires-Dist: networkx
Requires-Dist: GitPython
Requires-Dist: requests
Requires-Dist: packaging
Provides-Extra: dev
Requires-Dist: pytest; extra == "dev"
Dynamic: license-file
